{
  "timestamp": "2025-07-05T20:14:36.063443Z",
  "location": "Mauao Wave Buoy",
  "last_updated": "05/07/2025 20:14 UTC",
  "status": "partial_data",
  "data_quality": "incomplete",
  "scrape_attempt": "2025-07-05T20:14:36.063472Z",
  "raw_data": "Title,\nMauao Wave Buoy,\nTime,\n6/07/2025 08.11 ST\nMax wave height:\n1.5 m\nSig: wave height:\n11m\nperiod:\n8.3$\nTide:\n0.65 m\nWind:\n7 knts\nGust:\n8 knts\nDirection:\n219 Sw\nWater Temp:\n15.3 'C\nAir Temp:\n11.5 '",
  "parsed_data": {
    "title": "Title,",
    "location": "Mauao Wave Buoy,",
    "time_label": "Time,",
    "conditions": {
      "max_wave_height": null,
      "sig_wave_height": null,
      "wave_period": null,
      "tide": null,
      "wind_speed": null,
      "wind_gust": null,
      "wind_direction": "E",
      "water_temp": null,
      "air_temp": null
    },
    "raw_conditions": [
      "6/07/2025 08.11 ST",
      "Max wave height:",
      "1.5 m",
      "Sig: wave height:",
      "11m",
      "period:",
      "8.3$",
      "Tide:",
      "0.65 m",
      "Wind:",
      "7 knts",
      "Gust:",
      "8 knts",
      "Direction:",
      "219 Sw",
      "Water Temp:",
      "15.3 'C",
      "Air Temp:",
      "11.5 '"
    ]
  }
}