{
  "timestamp": "2025-07-12T18:18:56.483271Z",
  "location": "Mauao Wave Buoy",
  "last_updated": "12/07/2025 18:18 UTC",
  "status": "partial_data",
  "data_quality": "incomplete",
  "scrape_attempt": "2025-07-12T18:18:56.483298Z",
  "raw_data": "Title,\nMauao Wave Buoy,\nTime,\n13/07/2025 06.14 ST\nMax wave height:\n2.0 m\nSig: wave height:\n11m\nperiod:\n8.1 $\nTide:\n1.54m\nWind:\n6 knts\nGust:\n7 knts\nDirection:\n141 SE\nWater Temp:\n15.3 'C\nAir Temp:\n8.5 '",
  "parsed_data": {
    "title": "Title,",
    "location": "Mauao Wave Buoy,",
    "time_label": "Time,",
    "conditions": {
      "max_wave_height": null,
      "sig_wave_height": null,
      "wave_period": null,
      "tide": null,
      "wind_speed": null,
      "wind_gust": null,
      "wind_direction": "E",
      "water_temp": null,
      "air_temp": null
    },
    "raw_conditions": [
      "13/07/2025 06.14 ST",
      "Max wave height:",
      "2.0 m",
      "Sig: wave height:",
      "11m",
      "period:",
      "8.1 $",
      "Tide:",
      "1.54m",
      "Wind:",
      "6 knts",
      "Gust:",
      "7 knts",
      "Direction:",
      "141 SE",
      "Water Temp:",
      "15.3 'C",
      "Air Temp:",
      "8.5 '"
    ]
  }
}