{
  "timestamp": "2025-07-15T22:15:09.831181Z",
  "location": "Mauao Wave Buoy",
  "last_updated": "15/07/2025 22:15 UTC",
  "status": "partial_data",
  "data_quality": "incomplete",
  "scrape_attempt": "2025-07-15T22:15:09.831209Z",
  "raw_data": "Title,\nMauao Wave Buoy,\nTime,\n16/07/2025 10.12 ST\nMax wave height:\n0.7 m\nSig: wave height:\n0.5 m\nperiod:\n7.35\nTide:\n1.91 m\nWind:\n3 knts\nGust:\n7 knts\nDirection:\n187 $\nWater Temp:\n15.4 '\nAir Temp:\n14.2'",
  "parsed_data": {
    "title": "Title,",
    "location": "Mauao Wave Buoy,",
    "time_label": "Time,",
    "conditions": {
      "max_wave_height": null,
      "sig_wave_height": null,
      "wave_period": null,
      "tide": null,
      "wind_speed": null,
      "wind_gust": null,
      "wind_direction": "E",
      "water_temp": null,
      "air_temp": null
    },
    "raw_conditions": [
      "16/07/2025 10.12 ST",
      "Max wave height:",
      "0.7 m",
      "Sig: wave height:",
      "0.5 m",
      "period:",
      "7.35",
      "Tide:",
      "1.91 m",
      "Wind:",
      "3 knts",
      "Gust:",
      "7 knts",
      "Direction:",
      "187 $",
      "Water Temp:",
      "15.4 '",
      "Air Temp:",
      "14.2'"
    ]
  }
}