{
  "timestamp": "2025-07-13T07:26:05.288578Z",
  "location": "Mauao Wave Buoy",
  "last_updated": "13/07/2025 07:26 UTC",
  "status": "partial_data",
  "data_quality": "incomplete",
  "scrape_attempt": "2025-07-13T07:26:05.288604Z",
  "raw_data": "Title,\nMauao Wave Buoy,\nTime,\n13/07/2025 19.23 ST\nMax wave height:\n11m\nSig: wave height:\n0.9m\nperiod:\n7.9$\nTide:\n1.86 m\nWind:\nknts\nGust:\nknts\nDirection:\n343 NNW\nWater Temp:\n15.5 \"C\nAir Temp:\n12.8 '",
  "parsed_data": {
    "title": "Title,",
    "location": "Mauao Wave Buoy,",
    "time_label": "Time,",
    "conditions": {
      "max_wave_height": null,
      "sig_wave_height": null,
      "wave_period": null,
      "tide": null,
      "wind_speed": null,
      "wind_gust": null,
      "wind_direction": "E",
      "water_temp": null,
      "air_temp": null
    },
    "raw_conditions": [
      "13/07/2025 19.23 ST",
      "Max wave height:",
      "11m",
      "Sig: wave height:",
      "0.9m",
      "period:",
      "7.9$",
      "Tide:",
      "1.86 m",
      "Wind:",
      "knts",
      "Gust:",
      "knts",
      "Direction:",
      "343 NNW",
      "Water Temp:",
      "15.5 \"C",
      "Air Temp:",
      "12.8 '"
    ]
  }
}