{
  "timestamp": "2025-07-09T23:14:12.911890Z",
  "location": "Mauao Wave Buoy",
  "last_updated": "09/07/2025 23:14 UTC",
  "status": "partial_data",
  "data_quality": "incomplete",
  "scrape_attempt": "2025-07-09T23:14:12.911918Z",
  "raw_data": "Title,\nMauao Wave Buoy,\nTime,\n10/07/2025 11.09 ST\nMax wave height:\n17 m\nSig: wave height:\n1.2m\nperiod:\n8.6 $\nTide:\n0.64 m\nWind:\n15 knts\nGust:\n17 knts\nDirection:\n120 ESE\nWater Temp:\n14.4'C\nAir Temp:\n15.6 \"",
  "parsed_data": {
    "title": "Title,",
    "location": "Mauao Wave Buoy,",
    "time_label": "Time,",
    "conditions": {
      "max_wave_height": null,
      "sig_wave_height": null,
      "wave_period": null,
      "tide": null,
      "wind_speed": null,
      "wind_gust": null,
      "wind_direction": "E",
      "water_temp": null,
      "air_temp": null
    },
    "raw_conditions": [
      "10/07/2025 11.09 ST",
      "Max wave height:",
      "17 m",
      "Sig: wave height:",
      "1.2m",
      "period:",
      "8.6 $",
      "Tide:",
      "0.64 m",
      "Wind:",
      "15 knts",
      "Gust:",
      "17 knts",
      "Direction:",
      "120 ESE",
      "Water Temp:",
      "14.4'C",
      "Air Temp:",
      "15.6 \""
    ]
  }
}